uppd/__init__.py
uppd/py.typed
uppd/uppd.py
uppd-1.6.0.dist-info/LICENSE.txt
uppd-1.6.0.dist-info/METADATA
uppd-1.6.0.dist-info/WHEEL
uppd-1.6.0.dist-info/entry_points.txt
uppd-1.6.0.dist-info/top_level.txt
uppd-1.6.0.dist-info/RECORD
