Metadata-Version: 2.1
Name: uppd
Version: 1.6.0
Summary: Update dependencies and optional dependencies in pyproject.toml files.
Author-email: Janus Heide <janusheide@gmail.com>
Project-URL: Homepage, https://github.com/janusheide/uppd
Project-URL: Repository, https://github.com/janusheide/uppd
Project-URL: Changelog, https://github.com/janusheide/uppd/blob/main/NEWS.rst
Keywords: dependency management,maintenance,utility
Classifier: Development Status :: 5 - Production/Stable
Classifier: Intended Audience :: Developers
Classifier: License :: OSI Approved :: BSD License
Classifier: Operating System :: MacOS
Classifier: Operating System :: Microsoft :: Windows
Classifier: Operating System :: POSIX
Classifier: Operating System :: Unix
Classifier: Programming Language :: Python :: 3.8
Classifier: Programming Language :: Python :: 3.9
Classifier: Programming Language :: Python :: 3.10
Classifier: Programming Language :: Python :: 3.11
Classifier: Programming Language :: Python :: 3.12
Classifier: Programming Language :: Python :: 3.13
Classifier: Programming Language :: Python :: Implementation :: CPython
Classifier: Programming Language :: Python :: Implementation :: PyPy
Classifier: Topic :: Software Development
Classifier: Typing :: Typed
Requires-Python: >=3.8
License-File: LICENSE.txt
Requires-Dist: tomlkit>=0.10.0
Requires-Dist: aiohttp>=3.9.0
Requires-Dist: packaging>=24.2
Provides-Extra: test
Requires-Dist: dlister==1.3.0; extra == "test"
Requires-Dist: pytest==8.3.3; extra == "test"
Requires-Dist: pytest-aiohttp==1.0.5; extra == "test"
Requires-Dist: pytest-asyncio==0.24.0; extra == "test"
Requires-Dist: pytest-cov<=6.0.0,>=5.0.0; extra == "test"
Provides-Extra: dev
Requires-Dist: uppd[test]; extra == "dev"
Requires-Dist: brundle==1.3.0; extra == "dev"
Requires-Dist: isort==5.13.2; extra == "dev"
Requires-Dist: licensecheck==2024.3; extra == "dev"
Requires-Dist: mypy==1.13.0; extra == "dev"
Requires-Dist: ruff==0.8.1; extra == "dev"
Requires-Dist: bouillon==2.9.0; extra == "dev"
Requires-Dist: build==1.2.2.post1; extra == "dev"
Requires-Dist: twine==5.1.1; extra == "dev"
